<annotation>
	<folder>my-project-name</folder>
	<filename>Screenshot (202).png</filename>
	<path>/my-project-name/Screenshot (202).png</path>
	<source>
		<database>Unspecified</database>
	</source>
	<size>
		<width>389</width>
		<height>286</height>
		<depth>3</depth>
	</size>
	<object>
		<name>l</name>
		<pose>Unspecified</pose>
		<truncated>0</truncated>
		<difficult>0</difficult>
		<bndbox>
			<xmin>119</xmin>
			<ymin>131</ymin>
			<xmax>163</xmax>
			<ymax>167</ymax>
		</bndbox>
	</object>
	<object>
		<name>l</name>
		<pose>Unspecified</pose>
		<truncated>0</truncated>
		<difficult>0</difficult>
		<bndbox>
			<xmin>161</xmin>
			<ymin>72</ymin>
			<xmax>204</xmax>
			<ymax>114</ymax>
		</bndbox>
	</object>
	<object>
		<name>l</name>
		<pose>Unspecified</pose>
		<truncated>0</truncated>
		<difficult>0</difficult>
		<bndbox>
			<xmin>229</xmin>
			<ymin>98</ymin>
			<xmax>273</xmax>
			<ymax>142</ymax>
		</bndbox>
	</object>
	<object>
		<name>l</name>
		<pose>Unspecified</pose>
		<truncated>0</truncated>
		<difficult>0</difficult>
		<bndbox>
			<xmin>226</xmin>
			<ymin>168</ymin>
			<xmax>264</xmax>
			<ymax>213</ymax>
		</bndbox>
	</object>
	<object>
		<name>l</name>
		<pose>Unspecified</pose>
		<truncated>0</truncated>
		<difficult>0</difficult>
		<bndbox>
			<xmin>153</xmin>
			<ymin>190</ymin>
			<xmax>199</xmax>
			<ymax>230</ymax>
		</bndbox>
	</object>
</annotation>